{
    "name": "All Requests",
    "numberOfRequests": {
        "total": 11,
        "ok": 1,
        "ko": 10
    },
    "minResponseTime": {
        "total": 142,
        "ok": 546,
        "ko": 142
    },
    "maxResponseTime": {
        "total": 546,
        "ok": 546,
        "ko": 491
    },
    "meanResponseTime": {
        "total": 281,
        "ok": 546,
        "ko": 254
    },
    "standardDeviation": {
        "total": 124,
        "ok": 0,
        "ko": 95
    },
    "percentiles1": {
        "total": 261,
        "ok": 546,
        "ko": 255
    },
    "percentiles2": {
        "total": 291,
        "ok": 546,
        "ko": 276
    },
    "percentiles3": {
        "total": 519,
        "ok": 546,
        "ko": 405
    },
    "percentiles4": {
        "total": 541,
        "ok": 546,
        "ko": 474
    },
    "group1": {
    "name": "t < 800 ms",
    "htmlName": "t < 800 ms",
    "count": 1,
    "percentage": 9
},
    "group2": {
    "name": "800 ms <= t < 1200 ms",
    "htmlName": "t >= 800 ms <br> t < 1200 ms",
    "count": 0,
    "percentage": 0
},
    "group3": {
    "name": "t >= 1200 ms",
    "htmlName": "t >= 1200 ms",
    "count": 0,
    "percentage": 0
},
    "group4": {
    "name": "failed",
    "htmlName": "failed",
    "count": 10,
    "percentage": 91
},
    "meanNumberOfRequestsPerSecond": {
        "total": 2.75,
        "ok": 0.25,
        "ko": 2.5
    }
}