{
    "name": "All Requests",
    "numberOfRequests": {
        "total": 20,
        "ok": 10,
        "ko": 10
    },
    "minResponseTime": {
        "total": 638,
        "ok": 638,
        "ko": 30167
    },
    "maxResponseTime": {
        "total": 30354,
        "ok": 1357,
        "ko": 30354
    },
    "meanResponseTime": {
        "total": 15644,
        "ok": 977,
        "ko": 30311
    },
    "standardDeviation": {
        "total": 14668,
        "ok": 238,
        "ko": 53
    },
    "percentiles1": {
        "total": 15762,
        "ok": 960,
        "ko": 30333
    },
    "percentiles2": {
        "total": 30329,
        "ok": 1168,
        "ko": 30339
    },
    "percentiles3": {
        "total": 30348,
        "ok": 1318,
        "ko": 30351
    },
    "percentiles4": {
        "total": 30353,
        "ok": 1349,
        "ko": 30353
    },
    "group1": {
    "name": "t < 800 ms",
    "htmlName": "t < 800 ms",
    "count": 3,
    "percentage": 15
},
    "group2": {
    "name": "800 ms <= t < 1200 ms",
    "htmlName": "t >= 800 ms <br> t < 1200 ms",
    "count": 5,
    "percentage": 25
},
    "group3": {
    "name": "t >= 1200 ms",
    "htmlName": "t >= 1200 ms",
    "count": 2,
    "percentage": 10
},
    "group4": {
    "name": "failed",
    "htmlName": "failed",
    "count": 10,
    "percentage": 50
},
    "meanNumberOfRequestsPerSecond": {
        "total": 0.625,
        "ok": 0.3125,
        "ko": 0.3125
    }
}