{
  "type": "GROUP",
"name": "All Requests",
"path": "",
"pathFormatted": "group_missing-name-b06d1",
"stats": {
    "name": "All Requests",
    "numberOfRequests": {
        "total": 4,
        "ok": 2,
        "ko": 2
    },
    "minResponseTime": {
        "total": 39,
        "ok": 39,
        "ko": 164
    },
    "maxResponseTime": {
        "total": 611,
        "ok": 590,
        "ko": 611
    },
    "meanResponseTime": {
        "total": 351,
        "ok": 315,
        "ko": 388
    },
    "standardDeviation": {
        "total": 253,
        "ok": 276,
        "ko": 224
    },
    "percentiles1": {
        "total": 377,
        "ok": 315,
        "ko": 388
    },
    "percentiles2": {
        "total": 595,
        "ok": 452,
        "ko": 499
    },
    "percentiles3": {
        "total": 608,
        "ok": 562,
        "ko": 589
    },
    "percentiles4": {
        "total": 610,
        "ok": 584,
        "ko": 607
    },
    "group1": {
    "name": "t < 800 ms",
    "htmlName": "t < 800 ms",
    "count": 2,
    "percentage": 50
},
    "group2": {
    "name": "800 ms <= t < 1200 ms",
    "htmlName": "t >= 800 ms <br> t < 1200 ms",
    "count": 0,
    "percentage": 0
},
    "group3": {
    "name": "t >= 1200 ms",
    "htmlName": "t >= 1200 ms",
    "count": 0,
    "percentage": 0
},
    "group4": {
    "name": "failed",
    "htmlName": "failed",
    "count": 2,
    "percentage": 50
},
    "meanNumberOfRequestsPerSecond": {
        "total": 2.0,
        "ok": 1.0,
        "ko": 1.0
    }
},
"contents": {
"group_courthouse-api--33678": {
          "type": "GROUP",
"name": "Courthouse Api Request Group",
"path": "Courthouse Api Request Group",
"pathFormatted": "group_courthouse-api--33678",
"stats": {
    "name": "Courthouse Api Request Group",
    "numberOfRequests": {
        "total": 2,
        "ok": 0,
        "ko": 2
    },
    "minResponseTime": {
        "total": 203,
        "ok": 0,
        "ko": 203
    },
    "maxResponseTime": {
        "total": 1201,
        "ok": 0,
        "ko": 1201
    },
    "meanResponseTime": {
        "total": 702,
        "ok": 0,
        "ko": 702
    },
    "standardDeviation": {
        "total": 499,
        "ok": 0,
        "ko": 499
    },
    "percentiles1": {
        "total": 702,
        "ok": 0,
        "ko": 702
    },
    "percentiles2": {
        "total": 952,
        "ok": 0,
        "ko": 952
    },
    "percentiles3": {
        "total": 1151,
        "ok": 0,
        "ko": 1151
    },
    "percentiles4": {
        "total": 1191,
        "ok": 0,
        "ko": 1191
    },
    "group1": {
    "name": "t < 800 ms",
    "htmlName": "t < 800 ms",
    "count": 0,
    "percentage": 0
},
    "group2": {
    "name": "800 ms <= t < 1200 ms",
    "htmlName": "t >= 800 ms <br> t < 1200 ms",
    "count": 0,
    "percentage": 0
},
    "group3": {
    "name": "t >= 1200 ms",
    "htmlName": "t >= 1200 ms",
    "count": 0,
    "percentage": 0
},
    "group4": {
    "name": "failed",
    "htmlName": "failed",
    "count": 2,
    "percentage": 100
},
    "meanNumberOfRequestsPerSecond": {
        "total": 1.0,
        "ok": 0,
        "ko": 1.0
    }
},
"contents": {
"req_darts---api---c-18cbf": {
        "type": "REQUEST",
        "name": "DARTS - Api - CourtHouse:Post",
"path": "Courthouse Api Request Group / DARTS - Api - CourtHouse:Post",
"pathFormatted": "req_courthouse-api--b3a65",
"stats": {
    "name": "DARTS - Api - CourtHouse:Post",
    "numberOfRequests": {
        "total": 2,
        "ok": 2,
        "ko": 0
    },
    "minResponseTime": {
        "total": 39,
        "ok": 39,
        "ko": 0
    },
    "maxResponseTime": {
        "total": 590,
        "ok": 590,
        "ko": 0
    },
    "meanResponseTime": {
        "total": 315,
        "ok": 315,
        "ko": 0
    },
    "standardDeviation": {
        "total": 276,
        "ok": 276,
        "ko": 0
    },
    "percentiles1": {
        "total": 315,
        "ok": 315,
        "ko": 0
    },
    "percentiles2": {
        "total": 452,
        "ok": 452,
        "ko": 0
    },
    "percentiles3": {
        "total": 562,
        "ok": 562,
        "ko": 0
    },
    "percentiles4": {
        "total": 584,
        "ok": 584,
        "ko": 0
    },
    "group1": {
    "name": "t < 800 ms",
    "htmlName": "t < 800 ms",
    "count": 2,
    "percentage": 100
},
    "group2": {
    "name": "800 ms <= t < 1200 ms",
    "htmlName": "t >= 800 ms <br> t < 1200 ms",
    "count": 0,
    "percentage": 0
},
    "group3": {
    "name": "t >= 1200 ms",
    "htmlName": "t >= 1200 ms",
    "count": 0,
    "percentage": 0
},
    "group4": {
    "name": "failed",
    "htmlName": "failed",
    "count": 0,
    "percentage": 0
},
    "meanNumberOfRequestsPerSecond": {
        "total": 1.0,
        "ok": 1.0,
        "ko": 0
    }
}
    },"req_darts---api---c-20fc1": {
        "type": "REQUEST",
        "name": "DARTS - Api - CourtHouse:Post Redirect 1",
"path": "Courthouse Api Request Group / DARTS - Api - CourtHouse:Post Redirect 1",
"pathFormatted": "req_courthouse-api--f8e27",
"stats": {
    "name": "DARTS - Api - CourtHouse:Post Redirect 1",
    "numberOfRequests": {
        "total": 2,
        "ok": 0,
        "ko": 2
    },
    "minResponseTime": {
        "total": 164,
        "ok": 0,
        "ko": 164
    },
    "maxResponseTime": {
        "total": 611,
        "ok": 0,
        "ko": 611
    },
    "meanResponseTime": {
        "total": 388,
        "ok": 0,
        "ko": 388
    },
    "standardDeviation": {
        "total": 224,
        "ok": 0,
        "ko": 224
    },
    "percentiles1": {
        "total": 388,
        "ok": 0,
        "ko": 388
    },
    "percentiles2": {
        "total": 499,
        "ok": 0,
        "ko": 499
    },
    "percentiles3": {
        "total": 589,
        "ok": 0,
        "ko": 589
    },
    "percentiles4": {
        "total": 607,
        "ok": 0,
        "ko": 607
    },
    "group1": {
    "name": "t < 800 ms",
    "htmlName": "t < 800 ms",
    "count": 0,
    "percentage": 0
},
    "group2": {
    "name": "800 ms <= t < 1200 ms",
    "htmlName": "t >= 800 ms <br> t < 1200 ms",
    "count": 0,
    "percentage": 0
},
    "group3": {
    "name": "t >= 1200 ms",
    "htmlName": "t >= 1200 ms",
    "count": 0,
    "percentage": 0
},
    "group4": {
    "name": "failed",
    "htmlName": "failed",
    "count": 2,
    "percentage": 100
},
    "meanNumberOfRequestsPerSecond": {
        "total": 1.0,
        "ok": 0,
        "ko": 1.0
    }
}
    }
}

     }
}

}