{
    "name": "All Requests",
    "numberOfRequests": {
        "total": 2,
        "ok": 0,
        "ko": 2
    },
    "minResponseTime": {
        "total": 250,
        "ok": 0,
        "ko": 250
    },
    "maxResponseTime": {
        "total": 347,
        "ok": 0,
        "ko": 347
    },
    "meanResponseTime": {
        "total": 299,
        "ok": 0,
        "ko": 299
    },
    "standardDeviation": {
        "total": 49,
        "ok": 0,
        "ko": 49
    },
    "percentiles1": {
        "total": 299,
        "ok": 0,
        "ko": 299
    },
    "percentiles2": {
        "total": 323,
        "ok": 0,
        "ko": 323
    },
    "percentiles3": {
        "total": 342,
        "ok": 0,
        "ko": 342
    },
    "percentiles4": {
        "total": 346,
        "ok": 0,
        "ko": 346
    },
    "group1": {
    "name": "t < 800 ms",
    "htmlName": "t < 800 ms",
    "count": 0,
    "percentage": 0
},
    "group2": {
    "name": "800 ms <= t < 1200 ms",
    "htmlName": "t >= 800 ms <br> t < 1200 ms",
    "count": 0,
    "percentage": 0
},
    "group3": {
    "name": "t >= 1200 ms",
    "htmlName": "t >= 1200 ms",
    "count": 0,
    "percentage": 0
},
    "group4": {
    "name": "failed",
    "htmlName": "failed",
    "count": 2,
    "percentage": 100
},
    "meanNumberOfRequestsPerSecond": {
        "total": 2.0,
        "ok": 0,
        "ko": 2.0
    }
}